poly_pyhelpers/__init__.py
poly_pyhelpers/pyhelpers.py
poly_pyhelpers-0.1.5.dist-info/LICENSE
poly_pyhelpers-0.1.5.dist-info/METADATA
poly_pyhelpers-0.1.5.dist-info/WHEEL
poly_pyhelpers-0.1.5.dist-info/top_level.txt
poly_pyhelpers-0.1.5.dist-info/RECORD
