Metadata-Version: 2.1
Name: poly-pyhelpers
Version: 0.1.5
Summary: Some useful py methods
License: MIT License
Classifier: Development Status :: 3 - Alpha
Classifier: License :: OSI Approved :: MIT License
Classifier: Operating System :: OS Independent
Classifier: Programming Language :: Python :: 3.10
Classifier: Programming Language :: Python :: 3.11
Classifier: Programming Language :: Python :: 3.12
Classifier: Programming Language :: Python :: 3.13
Requires-Python: >=3.10
License-File: LICENSE
Requires-Dist: requests ~=2.31
Requires-Dist: pillow ~=10.1.0
Requires-Dist: io ~=0.1.2
